__init__.py
cograph_generator/__init__.py
cograph_generator/adjacency_g6.py
cograph_generator/generator.py
cograph_generator/structures.py
cograph_generator/utils.py
cograph_generator/visualization.py
cograph_generator-0.1.2.dist-info/licenses/LICENSE
cograph_generator-0.1.2.dist-info/METADATA
cograph_generator-0.1.2.dist-info/WHEEL
cograph_generator-0.1.2.dist-info/top_level.txt
cograph_generator-0.1.2.dist-info/RECORD
