Metadata-Version: 2.4
Name: cograph-generator
Version: 0.1.2
Summary: A high-performance Python library for generating and manipulating cographs, with canonical structure parsing and graph6 encoding.
Author: Fernando Souza Pimenta, Átila Arueira Jones
License: MIT License
Project-URL: Homepage, https://github.com/fsoupimenta/cograph-generator
Project-URL: Repository, https://github.com/fsoupimenta/cograph-generator
Keywords: cographs,graph theory,enumeration,graph6,combinatorics
Classifier: Programming Language :: Python :: 3
Classifier: License :: OSI Approved :: MIT License
Classifier: Operating System :: OS Independent
Classifier: Topic :: Scientific/Engineering
Classifier: Topic :: Scientific/Engineering :: Mathematics
Classifier: Intended Audience :: Science/Research
Requires-Python: >=3.9
License-File: LICENSE
Requires-Dist: numpy>=1.24
Requires-Dist: matplotlib>=3.7
Requires-Dist: networkx>=3.1
Dynamic: license-file
